LICENSE
README.md
setup.py
deepmediation/__init__.py
deepmediation/version.py
deepmediation.egg-info/PKG-INFO
deepmediation.egg-info/SOURCES.txt
deepmediation.egg-info/dependency_links.txt
deepmediation.egg-info/top_level.txt
deepmediation/src/__init__.py
deepmediation/src/utils.py